.bumpversion.cfg
.readthedocs.yaml
CONTRIBUTING.md
LICENSE
MANIFEST.in
Makefile
README.md
pyproject.toml
setup.py
docs/Makefile
docs/make.bat
docs/requirements.txt
docs/binder/timeline_egypt.csv
docs/binder/tutorial.ipynb
docs/binder/.ipynb_checkpoints/tutorial-checkpoint.ipynb
docs/source/conf.py
docs/source/date.rst
docs/source/event.rst
docs/source/graphics.rst
docs/source/index.rst
docs/source/timeline.rst
docs/source/_static/random_timeline.png
historical_timelines/__init__.py
historical_timelines/date.py
historical_timelines/event.py
historical_timelines/graphics.py
historical_timelines/timeline.py
historical_timelines.egg-info/PKG-INFO
historical_timelines.egg-info/SOURCES.txt
historical_timelines.egg-info/dependency_links.txt
historical_timelines.egg-info/requires.txt
historical_timelines.egg-info/top_level.txt
historical_timelines/tests/__init__.py
historical_timelines/tests/test_dates.py
historical_timelines/tests/test_events.py
historical_timelines/tests/test_graphics.py
historical_timelines/tests/test_integration.py
historical_timelines/tests/test_timelines.py
historical_timelines/tests/timeline_egypt.csv