Metadata-Version: 2.1
Name: historical-timelines
Version: 0.2.2
Summary: A Python package for making historical timelines
Home-page: UNKNOWN
Author: darthbeep
Author-email: darthbeep@gmail.com
License: UNKNOWN
Platform: UNKNOWN
License-File: LICENSE
